AUTHORS
LICENSE
README.md
isympy.py
pyproject.toml
setup.py
bin/isympy
data/TeXmacs/LICENSE
data/TeXmacs/bin/tm_sympy
data/TeXmacs/progs/init-sympy.scm
doc/Dockerfile.htmldoc
doc/Makefile
doc/README.rst
doc/apidoc.conf
doc/aptinstall.sh
doc/commit_hash.txt
doc/generate_logos.py
doc/make.bat
doc/requirements.txt
doc/api/conf.py
doc/api/index.rst
doc/cheatsheet/cheatsheet.tex
doc/cheatsheet/combinatoric_cheatsheet.tex
doc/ext/convert-svg-to-pdf.py
doc/ext/docscrape.py
doc/ext/docscrape_sphinx.py
doc/ext/numpydoc.py
doc/man/isympy.1
doc/man/isympy.xml
doc/src/citing.md
doc/src/conf.py
doc/src/index.rst
doc/src/install.md
doc/src/_pygments/styles.py
doc/src/_static/custom.css
doc/src/_static/sympylogo.png
doc/src/_static/sympylogo_big.png
doc/src/_templates/sidebar/versions.html
doc/src/contributing/debug.rst
doc/src/contributing/dependencies.md
doc/src/contributing/deprecations.md
doc/src/contributing/docstring.rst
doc/src/contributing/documentation-style-guide.rst
doc/src/contributing/index.md
doc/src/contributing/introduction-to-contributing.md
doc/src/contributing/new-contributors-guide/build-docs.rst
doc/src/contributing/new-contributors-guide/dev-setup.md
doc/src/contributing/new-contributors-guide/index.md
doc/src/contributing/new-contributors-guide/workflow-process.md
doc/src/contributing/new-contributors-guide/writing-tests.md
doc/src/explanation/active-deprecations.md
doc/src/explanation/best-practices.md
doc/src/explanation/glossary.md
doc/src/explanation/gotchas.rst
doc/src/explanation/index.rst
doc/src/explanation/solve_output.rst
doc/src/explanation/modules/physics/index.rst
doc/src/explanation/modules/physics/biomechanics/biomechanics.rst
doc/src/explanation/modules/physics/biomechanics/hill-type-muscle-model.svg
doc/src/explanation/modules/physics/biomechanics/hill-type-muscle-model.tex
doc/src/explanation/modules/physics/biomechanics/index.rst
doc/src/explanation/modules/physics/mechanics/PinJoint.svg
sympy_gouzhi.egg-info/PKG-INFO
sympy_gouzhi.egg-info/SOURCES.txt
sympy_gouzhi.egg-info/dependency_links.txt
sympy_gouzhi.egg-info/entry_points.txt
sympy_gouzhi.egg-info/not-zip-safe
sympy_gouzhi.egg-info/requires.txt
sympy_gouzhi.egg-info/top_level.txt