Metadata-Version: 2.1
Name: sympy-gouzhi
Version: 1.0
Summary: Computer algebra system (CAS) in Python
Home-page: https://sympy.org
Author: SymPy development team
Author-email: sympy@googlegroups.com
License: BSD
Project-URL: Source, https://github.com/majiayu000/sympy
Keywords: Math CAS
Classifier: License :: OSI Approved :: BSD License
Classifier: Operating System :: OS Independent
Classifier: Programming Language :: Python
Classifier: Topic :: Scientific/Engineering
Classifier: Topic :: Scientific/Engineering :: Mathematics
Classifier: Topic :: Scientific/Engineering :: Physics
Classifier: Programming Language :: Python :: 3
Classifier: Programming Language :: Python :: 3.8
Classifier: Programming Language :: Python :: 3.9
Classifier: Programming Language :: Python :: 3.10
Classifier: Programming Language :: Python :: 3.11
Classifier: Programming Language :: Python :: 3 :: Only
Classifier: Programming Language :: Python :: Implementation :: CPython
Classifier: Programming Language :: Python :: Implementation :: PyPy
Requires-Python: >=3.8
Provides-Extra: dev
License-File: LICENSE
License-File: AUTHORS
